django_rest_urltoken_auth/__init__.py
django_rest_urltoken_auth/admin.py
django_rest_urltoken_auth/apps.py
django_rest_urltoken_auth/authentication.py
django_rest_urltoken_auth/models.py
django_rest_urltoken_auth/permissions.py
django_rest_urltoken_auth/views.py
django_rest_urltoken_auth/migrations/0001_initial.py
django_rest_urltoken_auth/migrations/__init__.py
django_rest_urltoken_auth/tests/__init__.py
django_rest_urltoken_auth/tests/tests.py
django_rest_urltoken_auth-0.1.0.dist-info/LICENSE
django_rest_urltoken_auth-0.1.0.dist-info/METADATA
django_rest_urltoken_auth-0.1.0.dist-info/WHEEL
django_rest_urltoken_auth-0.1.0.dist-info/top_level.txt
django_rest_urltoken_auth-0.1.0.dist-info/RECORD
