Metadata-Version: 2.1
Name: django-rest-urltoken-auth
Version: 0.1.0
Summary: Django REST app to allow authentication with url tokens
Home-page: https://github.com/project-cece/django-rest-urltoken-auth
Author: Marcella Wijngaarden
Author-email: marcellawijngaarden@hotmail.com
License: BSD-3-Clause
Platform: UNKNOWN
Classifier: Environment :: Web Environment
Classifier: Framework :: Django
Classifier: Framework :: Django :: 3.0
Classifier: Intended Audience :: Developers
Classifier: Operating System :: OS Independent
Classifier: Programming Language :: Python :: 3.6
Classifier: Programming Language :: Python :: 3.7
Classifier: Programming Language :: Python :: 3.8
Classifier: Topic :: Internet :: WWW/HTTP
Classifier: Topic :: Internet :: WWW/HTTP :: Dynamic Content
Requires-Python: >=3.6
Requires-Dist: Django (>=3.0)
